{
    "request": {
        "url": "http://api-int:7000/search.json?q=%23irritate&window=a&apikey=09C43A9B270A470B8EB8F2946A9369F3&type=tweet&offset=950",
        "resource": "search",
        "response_type": "json",
        "parameters": {
            "q": "#irritate",
            "window": "a",
            "type": "tweet",
            "offset": "950"
        }
    },
    "response": {
        "perpage": 10,
        "list": [
            {
                "hits": 2,
                "firstpost_date": 1339769226,
                "title": "You know what.. Im actually gonna miss Mrs Ford.. #syke #LolJk #wanker #twatcut #manhair #fathem #trig #irritate #veggie #youvegotpoorvocab",
                "url": "http://twitter.com/chasemystatus/status/213633734686150656",
                "trackback_date": 1339769226,
                "trackback_total": 1,
                "url_expansions": [],
                "target_birth_date": 1339769226,
                "content": "You know what.. Im actually gonna miss Mrs Ford.. #syke #LolJk #wanker #twatcut #manhair #fathem #trig #irritate #veggie #youvegotpoorvocab",
                "mytype": "tweet",
                "score": 5.275992,
                "topsy_author_img": "http://pbs.twimg.com/profile_images/471423594183278592/ZMzZ8aMR_normal.jpeg",
                "trackback_permalink": "http://twitter.com/chasemystatus/status/213633734686150656",
                "trackback_author_url": "http://twitter.com/_jamessisterson",
                "highlight": "You know what.. Im actually gonna miss Mrs Ford.. #syke #LolJk #wanker #twatcut #manhair #fathem #trig #irritate #veggie",
                "topsy_author_url": "http://topsy.com/twitter/_jamessisterson",
                "topsy_trackback_url": "http://topsy.com/trackback?url=http%3A//twitter.com/chasemystatus/status/213633734686150656",
                "trackback_author_name": "J a m e s",
                "trackback_author_nick": "_jamessisterson"
            },
            {
                "hits": 3,
                "firstpost_date": 1346234826,
                "title": "Hate it when you have to listen to someone's boring story and then the second you start talking, they become otherwise occupied #irritate",
                "url": "http://twitter.com/fionaa_jones/status/240752427387719680",
                "trackback_date": 1346234826,
                "trackback_total": 3,
                "url_expansions": [],
                "target_birth_date": 1346234826,
                "content": "Hate it when you have to listen to someone's boring story and then the second you start talking, they become otherwise occupied #irritate",
                "mytype": "tweet",
                "score": 5.268542,
                "topsy_author_img": "http://pbs.twimg.com/profile_images/459041750624247808/0_9BAHf1_normal.jpeg",
                "trackback_permalink": "http://twitter.com/fionaa_jones/status/240752427387719680",
                "trackback_author_url": "http://twitter.com/fionaa_jones",
                "highlight": "Hate it when you have to listen to someone's boring story and then the second you start talking, they become otherwise occupied",
                "topsy_author_url": "http://topsy.com/twitter/fionaa_jones",
                "topsy_trackback_url": "http://topsy.com/trackback?url=http%3A//twitter.com/fionaa_jones/status/240752427387719680",
                "trackback_author_name": "Fiona Jones",
                "trackback_author_nick": "fionaa_jones"
            },
            {
                "hits": 2,
                "firstpost_date": 1389910233,
                "title": "Cba with some people #irritate #annoy me \ud83d\ude04",
                "url": "http://twitter.com/capriamanda/status/423940363376947200",
                "trackback_date": 1389910233,
                "trackback_total": 1,
                "url_expansions": [],
                "target_birth_date": 1389910233,
                "content": "Cba with some people #irritate #annoy me \ud83d\ude04",
                "mytype": "tweet",
                "score": 5.262898,
                "topsy_author_img": "http://pbs.twimg.com/profile_images/473200649245847552/6XuRfOEX_normal.jpeg",
                "trackback_permalink": "http://twitter.com/capriamanda/status/423940363376947200",
                "trackback_author_url": "http://twitter.com/capriamanda",
                "highlight": "Cba with some people #irritate #annoy me \ud83d\ude04",
                "topsy_author_url": "http://topsy.com/twitter/capriamanda",
                "topsy_trackback_url": "http://topsy.com/trackback?url=http%3A//twitter.com/capriamanda/status/423940363376947200",
                "trackback_author_name": "Capri Lance\u30c4",
                "trackback_author_nick": "capriamanda"
            },
            {
                "hits": 2,
                "firstpost_date": 1324285913,
                "title": "#excessive #use #of #hash tags #irritate #me",
                "url": "http://twitter.com/nickpearson91/status/148692016488910848",
                "trackback_date": 1324637088,
                "trackback_total": 2,
                "url_expansions": [],
                "target_birth_date": 1324285913,
                "content": "RT @Nickpearson91: #excessive #use #of #hash tags #irritate #me",
                "mytype": "tweet",
                "score": 5.2613425,
                "topsy_author_img": "http://pbs.twimg.com/profile_images/470232303357415425/pWm9BD3y_normal.jpeg",
                "trackback_permalink": "http://twitter.com/Beanieex3/status/150164947236700160",
                "trackback_author_url": "http://twitter.com/colleennleonard",
                "highlight": "#excessive #use #of #hash tags #irritate",
                "topsy_author_url": "http://topsy.com/twitter/colleennleonard",
                "topsy_trackback_url": "http://topsy.com/trackback?url=http%3A//twitter.com/nickpearson91/status/148692016488910848",
                "trackback_author_name": "Colleen",
                "trackback_author_nick": "colleennleonard"
            },
            {
                "hits": 2,
                "firstpost_date": 1370443661,
                "title": "Some ppl r jus born to #irritate others \ud83d\ude21\ud83d\udc4a\ud83d\ude20\ud83d\ude16\ud83d\ude21\ud83d\ude20\ud83d\ude16",
                "url": "http://twitter.com/prinathan/status/342291641727582208",
                "trackback_date": 1370443661,
                "trackback_total": 3,
                "url_expansions": [],
                "target_birth_date": 1370443661,
                "content": "Some ppl r jus born to #irritate others \ud83d\ude21\ud83d\udc4a\ud83d\ude20\ud83d\ude16\ud83d\ude21\ud83d\ude20\ud83d\ude16",
                "mytype": "tweet",
                "score": 5.259241,
                "topsy_author_img": "http://pbs.twimg.com/profile_images/461740322045693955/lclOMHqm_normal.jpeg",
                "trackback_permalink": "http://twitter.com/prinathan/status/342291641727582208",
                "trackback_author_url": "http://twitter.com/prinathan",
                "highlight": "Some ppl r jus born to #irritate others \ud83d\ude21\ud83d\udc4a\ud83d\ude20\ud83d\ude16\ud83d\ude21\ud83d\ude20\ud83d\ude16",
                "topsy_author_url": "http://topsy.com/twitter/prinathan",
                "topsy_trackback_url": "http://topsy.com/trackback?url=http%3A//twitter.com/prinathan/status/342291641727582208",
                "trackback_author_name": "Priya Manjunathan",
                "trackback_author_nick": "prinathan"
            },
            {
                "hits": 1,
                "firstpost_date": 1311430167,
                "title": "why are #blokes like #laxatives? coz the both #irritate the shit #outofyou",
                "url": "http://twitter.com/fakenicole82/status/94771109152559106",
                "trackback_date": 1311430167,
                "trackback_total": 1,
                "url_expansions": [],
                "target_birth_date": 1311430167,
                "content": "why are #blokes like #laxatives? coz the both #irritate the shit #outofyou",
                "mytype": "tweet",
                "score": 5.259027,
                "topsy_author_img": "http://pbs.twimg.com/profile_images/378800000722815067/8be3ac0e5808dd259049d2bd4b2adb22_normal.jpeg",
                "trackback_permalink": "http://twitter.com/fakenicole82/status/94771109152559106",
                "trackback_author_url": "http://twitter.com/niccfc",
                "highlight": "why are #blokes like #laxatives? coz the both #irritate the shit",
                "topsy_author_url": "http://topsy.com/twitter/niccfc",
                "topsy_trackback_url": "http://topsy.com/trackback?url=http%3A//twitter.com/fakenicole82/status/94771109152559106",
                "trackback_author_name": "nic",
                "trackback_author_nick": "niccfc"
            },
            {
                "hits": 1,
                "firstpost_date": 1354952328,
                "title": "#Longest #Monotomous #Baren road I have even been on!!! #Yawn!!! Now I can #irritate my sister! Yay! @Angel8666",
                "url": "http://twitter.com/woutervandermer/status/277316283186421760",
                "trackback_date": 1354952328,
                "trackback_total": 1,
                "url_expansions": [],
                "target_birth_date": 1354952328,
                "content": "#Longest #Monotomous #Baren road I have even been on!!! #Yawn!!! Now I can #irritate my sister! Yay! @Angel8666",
                "mytype": "tweet",
                "score": 5.258131,
                "topsy_author_img": "http://pbs.twimg.com/profile_images/445059853971894272/DpQdbGps_normal.jpeg",
                "trackback_permalink": "http://twitter.com/woutervandermer/status/277316283186421760",
                "trackback_author_url": "http://twitter.com/woutervandermer",
                "highlight": "#Longest #Monotomous #Baren road I have even been on!!! #Yawn!!! Now I can #irritate my sister! Yay! @Angel8666",
                "topsy_author_url": "http://topsy.com/twitter/woutervandermer",
                "topsy_trackback_url": "http://topsy.com/trackback?url=http%3A//twitter.com/woutervandermer/status/277316283186421760",
                "trackback_author_name": "Wouter van der Merwe",
                "trackback_author_nick": "woutervandermer"
            },
            {
                "hits": 2,
                "firstpost_date": 1356803263,
                "title": "slow texters can really #IRRITATE me , like on some #RS",
                "url": "http://twitter.com/heartlessmuch_x/status/285079667000614912",
                "trackback_date": 1356803263,
                "trackback_total": 1,
                "url_expansions": [],
                "target_birth_date": 1356803263,
                "content": "slow texters can really #IRRITATE me , like on some #RS",
                "mytype": "tweet",
                "score": 5.2568126,
                "topsy_author_img": "http://pbs.twimg.com/profile_images/467896550052462592/ts2nhZ2v_normal.jpeg",
                "trackback_permalink": "http://twitter.com/heartLESSmuch_x/status/285079667000614912",
                "trackback_author_url": "http://twitter.com/heartlessmuch_x",
                "highlight": "slow texters can really #IRRITATE me , like on some",
                "topsy_author_url": "http://topsy.com/twitter/heartlessmuch_x",
                "topsy_trackback_url": "http://topsy.com/trackback?url=http%3A//twitter.com/heartlessmuch_x/status/285079667000614912",
                "trackback_author_name": ". . .",
                "trackback_author_nick": "heartlessmuch_x"
            },
            {
                "hits": 1,
                "firstpost_date": 1350406410,
                "title": "Why does everyone keep asking me when I'm going back!!? @*$Y@O#*&amp;^!(*!&amp; So annoyed!! I'm not ready to plan other trips!! #irritate #brokeass",
                "url": "http://twitter.com/bzqueendom/status/258249320430718976",
                "trackback_date": 1350406410,
                "trackback_total": 1,
                "url_expansions": [],
                "target_birth_date": 1350406410,
                "content": "Why does everyone keep asking me when I'm going back!!? @*$Y@O#*&amp;^!(*!&amp; So annoyed!! I'm not ready to plan other trips!! #irritate #brokeass",
                "mytype": "tweet",
                "score": 5.252123,
                "topsy_author_img": "http://pbs.twimg.com/profile_images/467796818953113600/x_IK5zqE_normal.jpeg",
                "trackback_permalink": "http://twitter.com/bzqueendom/status/258249320430718976",
                "trackback_author_url": "http://twitter.com/bzqueend0m",
                "highlight": "Why does everyone keep asking me when I'm going back!!? @*$Y@O#*&amp;^!(*!&amp; So annoyed!! I'm not ready to plan other trips!! #irritate",
                "topsy_author_url": "http://topsy.com/twitter/bzqueend0m",
                "topsy_trackback_url": "http://topsy.com/trackback?url=http%3A//twitter.com/bzqueendom/status/258249320430718976",
                "trackback_author_name": "Alinda",
                "trackback_author_nick": "bzqueend0m"
            },
            {
                "hits": 3,
                "firstpost_date": 1358704287,
                "title": "he bout to #IRRITATE me -.-",
                "url": "http://twitter.com/heartlessmuch_x/status/293053138364157952",
                "trackback_date": 1358704287,
                "trackback_total": 2,
                "url_expansions": [],
                "target_birth_date": 1358704287,
                "content": "he bout to #IRRITATE me -.-",
                "mytype": "tweet",
                "score": 5.249615,
                "topsy_author_img": "http://pbs.twimg.com/profile_images/467896550052462592/ts2nhZ2v_normal.jpeg",
                "trackback_permalink": "http://twitter.com/heartLESSmuch_x/status/293053138364157952",
                "trackback_author_url": "http://twitter.com/heartlessmuch_x",
                "highlight": "he bout to #IRRITATE me -.-",
                "topsy_author_url": "http://topsy.com/twitter/heartlessmuch_x",
                "topsy_trackback_url": "http://topsy.com/trackback?url=http%3A//twitter.com/heartlessmuch_x/status/293053138364157952",
                "trackback_author_name": ". . .",
                "trackback_author_nick": "heartlessmuch_x"
            }
        ],
        "last_offset": 10,
        "window": "a",
        "offset": 950,
        "hidden": 0,
        "total": 5693,
        "page": 1
    }
}