{
    "request": {
        "url": "http://api-int:7000/search.json?q=%23tantalize&window=a&apikey=09C43A9B270A470B8EB8F2946A9369F3&type=tweet&offset=240",
        "resource": "search",
        "response_type": "json",
        "parameters": {
            "q": "#tantalize",
            "window": "a",
            "type": "tweet",
            "offset": "240"
        }
    },
    "response": {
        "perpage": 10,
        "list": [
            {
                "hits": 1,
                "firstpost_date": 1361039151,
                "title": "#TMNT @ #Tantalize http://t.co/jCSPKLUf",
                "url": "http://twitter.com/tas_mo1/status/302846266562465792",
                "trackback_date": 1361039151,
                "trackback_total": 0,
                "url_expansions": [
                    {
                        "url": "http://t.co/jCSPKLUf",
                        "expanded_url": "http://twitter.com/tas_mo1/status/302846266562465792/photo/1",
                        "display_url": "pic.twitter.com/jCSPKLUf"
                    }
                ],
                "target_birth_date": 1361039151,
                "content": "#TMNT @ #Tantalize http://t.co/jCSPKLUf",
                "mytype": "tweet",
                "score": 4.985644,
                "topsy_author_img": "http://pbs.twimg.com/profile_images/457363640723578881/OSp6jXHO_normal.jpeg",
                "trackback_permalink": "http://twitter.com/tas_mo1/status/302846266562465792",
                "trackback_author_url": "http://twitter.com/tiffanysinasac",
                "highlight": "#TMNT @ #Tantalize",
                "topsy_author_url": "http://topsy.com/twitter/tiffanysinasac",
                "topsy_trackback_url": "http://topsy.com/trackback?url=http%3A//twitter.com/tas_mo1/status/302846266562465792",
                "trackback_author_name": "Tiffany S",
                "trackback_author_nick": "tiffanysinasac"
            },
            {
                "hits": 1,
                "firstpost_date": 1373553614,
                "title": "Don't Worry... Be TANNIE! #TANtalize http://t.co/k0Ij5LOiaJ",
                "url": "http://twitter.com/tantalizetan/status/355335730286964736",
                "trackback_date": 1373553614,
                "trackback_total": 0,
                "url_expansions": [
                    {
                        "url": "http://t.co/k0Ij5LOiaJ",
                        "display_url": "pic.twitter.com/k0Ij5LOiaJ",
                        "expanded_url": "http://twitter.com/TANtalizeTan/status/355335730286964736/photo/1",
                        "topsy_expanded_url": "http://pbs.twimg.com/media/BO5n9swCMAAX0vK.jpg"
                    }
                ],
                "target_birth_date": 1373553614,
                "content": "Don't Worry... Be TANNIE! #TANtalize http://t.co/k0Ij5LOiaJ",
                "mytype": "tweet",
                "score": 4.985403,
                "topsy_author_img": "http://pbs.twimg.com/profile_images/2478585656/6ridmvkk6mef1gljpf99_normal.jpeg",
                "trackback_permalink": "http://twitter.com/TANtalizeTan/status/355335730286964736",
                "trackback_author_url": "http://twitter.com/tantalizetan",
                "highlight": "Don't Worry... Be TANNIE! #TANtalize",
                "topsy_author_url": "http://topsy.com/twitter/tantalizetan",
                "topsy_trackback_url": "http://topsy.com/trackback?url=http%3A//twitter.com/tantalizetan/status/355335730286964736",
                "trackback_author_name": "TANtalize Tanning",
                "trackback_author_nick": "tantalizetan"
            },
            {
                "hits": 1,
                "firstpost_date": 1376043115,
                "title": "Love my nails jade did for me! #tantalize #work #happygirl http://t.co/Q0c2zdg1BK",
                "url": "http://twitter.com/sharneyjp/status/365777454775812096",
                "trackback_date": 1376043115,
                "trackback_total": 0,
                "url_expansions": [
                    {
                        "url": "http://t.co/Q0c2zdg1BK",
                        "display_url": "instagram.com/p/cyeFMKDiVc/",
                        "expanded_url": "http://instagram.com/p/cyeFMKDiVc/",
                        "topsy_expanded_url": "http://instagram.com/p/cyeFMKDiVc/"
                    }
                ],
                "target_birth_date": 1376043115,
                "content": "Love my nails jade did for me! #tantalize #work #happygirl http://t.co/Q0c2zdg1BK",
                "mytype": "tweet",
                "score": 4.985109,
                "topsy_author_img": "http://pbs.twimg.com/profile_images/471365043561709568/1jD6P_HW_normal.jpeg",
                "trackback_permalink": "http://twitter.com/Sharneyjp/status/365777454775812096",
                "trackback_author_url": "http://twitter.com/sharneyjp",
                "highlight": "Love my nails jade did for me! #tantalize #work #happygirl",
                "topsy_author_url": "http://topsy.com/twitter/sharneyjp",
                "topsy_trackback_url": "http://topsy.com/trackback?url=http%3A//twitter.com/sharneyjp/status/365777454775812096",
                "trackback_author_name": "Sharney",
                "trackback_author_nick": "sharneyjp"
            },
            {
                "hits": 1,
                "firstpost_date": 1377984387,
                "title": "#gogo #tantalize  iDream Makeup line!! https://t.co/5eTFPJ32ak",
                "url": "http://twitter.com/tantalize_dance/status/373919739162398720",
                "trackback_date": 1377984387,
                "trackback_total": 0,
                "url_expansions": [
                    {
                        "url": "https://t.co/5eTFPJ32ak",
                        "display_url": "vine.co/v/h5OQjalj0lW",
                        "expanded_url": "https://vine.co/v/h5OQjalj0lW",
                        "topsy_expanded_url": "https://vine.co/v/h5OQjalj0lW"
                    }
                ],
                "target_birth_date": 1377984387,
                "content": "#gogo #tantalize  iDream Makeup line!! https://t.co/5eTFPJ32ak",
                "mytype": "tweet",
                "score": 4.985094,
                "topsy_author_img": "http://pbs.twimg.com/profile_images/378800000091965609/4851fcee7de20299bfcf298ea9e956ad_normal.jpeg",
                "trackback_permalink": "http://twitter.com/Tantalize_Dance/status/373919739162398720",
                "trackback_author_url": "http://twitter.com/tantalize_dance",
                "highlight": "#gogo #tantalize iDream Makeup line!!",
                "topsy_author_url": "http://topsy.com/twitter/tantalize_dance",
                "topsy_trackback_url": "http://topsy.com/trackback?url=http%3A//twitter.com/tantalize_dance/status/373919739162398720",
                "trackback_author_name": "Tantalize Dance",
                "trackback_author_nick": "tantalize_dance"
            },
            {
                "hits": 1,
                "firstpost_date": 1392018183,
                "title": "#Tantalize @SavinduSAPRE http://t.co/gs336lCl9G",
                "url": "http://twitter.com/dishan_esada/status/432781744635260928",
                "trackback_date": 1392018183,
                "trackback_total": 0,
                "url_expansions": [
                    {
                        "url": "http://t.co/gs336lCl9G",
                        "display_url": "pic.twitter.com/gs336lCl9G",
                        "expanded_url": "http://twitter.com/dishan_esada/status/432781744635260928/photo/1",
                        "topsy_expanded_url": "http://pbs.twimg.com/media/BgGMtCRCMAAoVF-.jpg"
                    }
                ],
                "target_birth_date": 1392018183,
                "content": "#Tantalize @SavinduSAPRE http://t.co/gs336lCl9G",
                "mytype": "tweet",
                "score": 4.984661,
                "topsy_author_img": "http://pbs.twimg.com/profile_images/432890722719522816/jgtFf532_normal.jpeg",
                "trackback_permalink": "http://twitter.com/dishan_esada/status/432781744635260928",
                "trackback_author_url": "http://twitter.com/dishan_esada",
                "highlight": "#Tantalize @SavinduSAPRE",
                "topsy_author_url": "http://topsy.com/twitter/dishan_esada",
                "topsy_trackback_url": "http://topsy.com/trackback?url=http%3A//twitter.com/dishan_esada/status/432781744635260928",
                "trackback_author_name": "Dishan",
                "trackback_author_nick": "dishan_esada"
            },
            {
                "hits": 1,
                "firstpost_date": 1391977055,
                "title": "#Tantalize\u2665 http://t.co/zJ5WfrSoMN",
                "url": "http://twitter.com/dinoulsm/status/432609243271667712",
                "trackback_date": 1391977055,
                "trackback_total": 0,
                "url_expansions": [
                    {
                        "url": "http://t.co/zJ5WfrSoMN",
                        "display_url": "pic.twitter.com/zJ5WfrSoMN",
                        "expanded_url": "http://twitter.com/DinouLsm/status/432609243271667712/photo/1",
                        "topsy_expanded_url": "http://pbs.twimg.com/media/BgDv0JACIAAJkwp.jpg"
                    }
                ],
                "target_birth_date": 1391977055,
                "content": "#Tantalize\u2665 http://t.co/zJ5WfrSoMN",
                "mytype": "tweet",
                "score": 4.984661,
                "topsy_author_img": "http://pbs.twimg.com/profile_images/462214691033333760/ChM2dMqQ_normal.jpeg",
                "trackback_permalink": "http://twitter.com/DinouLsm/status/432609243271667712",
                "trackback_author_url": "http://twitter.com/dinoulsm",
                "highlight": "#Tantalize\u2665",
                "topsy_author_url": "http://topsy.com/twitter/dinoulsm",
                "topsy_trackback_url": "http://topsy.com/trackback?url=http%3A//twitter.com/dinoulsm/status/432609243271667712",
                "trackback_author_name": "Amandine",
                "trackback_author_nick": "dinoulsm"
            },
            {
                "hits": 2,
                "firstpost_date": 1380959246,
                "title": "Three Groups have been chosen as finalists for the Group Singing Category for #tantalize 2013! @APIITsl",
                "url": "http://twitter.com/tantalize2013/status/386397202211696640",
                "trackback_date": 1380959246,
                "trackback_total": 1,
                "url_expansions": [],
                "target_birth_date": 1380959246,
                "content": "Three Groups have been chosen as finalists for the Group Singing Category for #tantalize 2013! @APIITsl",
                "mytype": "tweet",
                "score": 4.981273,
                "topsy_author_img": "http://pbs.twimg.com/profile_images/378800000495012700/97f2f8dece53e08507940360adca70f3_normal.jpeg",
                "trackback_permalink": "http://twitter.com/Tantalize2013/status/386397202211696640",
                "trackback_author_url": "http://twitter.com/tantalize2013",
                "highlight": "Three Groups have been chosen as finalists for the Group Singing Category for #tantalize 2013! @APIITsl",
                "topsy_author_url": "http://topsy.com/twitter/tantalize2013",
                "topsy_trackback_url": "http://topsy.com/trackback?url=http%3A//twitter.com/tantalize2013/status/386397202211696640",
                "trackback_author_name": "Tantalize ",
                "trackback_author_nick": "tantalize2013"
            },
            {
                "hits": 2,
                "firstpost_date": 1351581901,
                "title": "Everywhere people selling tickets for tantalize....  #tantalize #apiitsl @APIITsl",
                "url": "http://twitter.com/ucanhamza/status/263179686706827264",
                "trackback_date": 1351581901,
                "trackback_total": 2,
                "url_expansions": [],
                "target_birth_date": 1351581901,
                "content": "Everywhere people selling tickets for tantalize....  #tantalize #apiitsl @APIITsl",
                "mytype": "tweet",
                "score": 4.9807267,
                "topsy_author_img": "http://pbs.twimg.com/profile_images/378800000608833415/d6a855ae1ab93e344ea9b75b543b5c77_normal.jpeg",
                "trackback_permalink": "http://twitter.com/ucanhamza/status/263179686706827264",
                "trackback_author_url": "http://twitter.com/ucanhamza",
                "highlight": "Everywhere people selling tickets for tantalize.... #tantalize #apiitsl @APIITsl",
                "topsy_author_url": "http://topsy.com/twitter/ucanhamza",
                "topsy_trackback_url": "http://topsy.com/trackback?url=http%3A//twitter.com/ucanhamza/status/263179686706827264",
                "trackback_author_name": "Hamza Madany",
                "trackback_author_nick": "ucanhamza"
            },
            {
                "hits": 1,
                "firstpost_date": 1302627154,
                "title": "From blah to bite #tantalize",
                "url": "http://twitter.com/iamdianne07/status/57848593981247488",
                "trackback_date": 1302627154,
                "trackback_total": 0,
                "url_expansions": [],
                "target_birth_date": 1302627154,
                "content": "From blah to bite #tantalize",
                "mytype": "tweet",
                "score": 4.9779444,
                "topsy_author_img": "http://a0.twimg.com/profile_images/2675899413/51e0cb189c99fa495e28f1ed33908cde_normal.jpeg",
                "trackback_permalink": "http://twitter.com/iamdianne07/status/57848593981247488",
                "trackback_author_url": "http://twitter.com/iamdianne07",
                "highlight": "From blah to bite",
                "topsy_author_url": "http://topsy.com/twitter/iamdianne07",
                "topsy_trackback_url": "http://topsy.com/trackback?url=http%3A//twitter.com/iamdianne07/status/57848593981247488",
                "trackback_author_name": "dianne",
                "trackback_author_nick": "iamdianne07"
            },
            {
                "hits": 1,
                "firstpost_date": 1299263537,
                "title": "one word that describes me.  #tantalize.  get into it.",
                "url": "http://twitter.com/louieboomboom/status/43740561286504448",
                "trackback_date": 1299263537,
                "trackback_total": 0,
                "url_expansions": [],
                "target_birth_date": 1299263537,
                "content": "one word that describes me.  #tantalize.  get into it.",
                "mytype": "tweet",
                "score": 4.977923,
                "topsy_author_img": "http://a0.twimg.com/profile_images/2903038964/a7e5b3424496abdaa1047c738f9ef9c3_normal.jpeg",
                "trackback_permalink": "http://twitter.com/LouieBoomBoom/status/43740561286504448",
                "trackback_author_url": "http://twitter.com/louieboomboom",
                "highlight": "one word that describes me. #tantalize. get into it.",
                "topsy_author_url": "http://topsy.com/twitter/louieboomboom",
                "topsy_trackback_url": "http://topsy.com/trackback?url=http%3A//twitter.com/louieboomboom/status/43740561286504448",
                "trackback_author_name": "Louie Boom Boom",
                "trackback_author_nick": "louieboomboom"
            }
        ],
        "last_offset": 10,
        "window": "a",
        "offset": 240,
        "hidden": 0,
        "total": 703,
        "page": 1
    }
}