{
    "request": {
        "url": "http://api-int:7000/search.json?q=%23prejudicial&window=a&apikey=09C43A9B270A470B8EB8F2946A9369F3&type=tweet&offset=190",
        "resource": "search",
        "response_type": "json",
        "parameters": {
            "q": "#prejudicial",
            "window": "a",
            "type": "tweet",
            "offset": "190"
        }
    },
    "response": {
        "perpage": 10,
        "list": [
            {
                "hits": 1,
                "firstpost_date": 1379221030,
                "title": "Getting home at midnight, just to get back up in the morning and go right back to school #volleyball #prejudicial #busy",
                "url": "http://twitter.com/aseanard/status/379106596011642880",
                "trackback_date": 1379221030,
                "trackback_total": 0,
                "url_expansions": [],
                "target_birth_date": 1379221030,
                "content": "Getting home at midnight, just to get back up in the morning and go right back to school #volleyball #prejudicial #busy",
                "mytype": "tweet",
                "score": 4.896673,
                "topsy_author_img": "http://pbs.twimg.com/profile_images/424044829195378688/8ZxGJ3JP_normal.jpeg",
                "trackback_permalink": "http://twitter.com/aseanard/status/379106596011642880",
                "trackback_author_url": "http://twitter.com/aseanard",
                "highlight": "Getting home at midnight, just to get back up in the morning and go right back to school #volleyball #prejudicial",
                "topsy_author_url": "http://topsy.com/twitter/aseanard",
                "topsy_trackback_url": "http://topsy.com/trackback?url=http%3A//twitter.com/aseanard/status/379106596011642880",
                "trackback_author_name": "Alli Seanard",
                "trackback_author_nick": "aseanard"
            },
            {
                "hits": 1,
                "firstpost_date": 1394042850,
                "title": "Then I had to say judicial, and judiciary 100 more times as a punishment. #prejudicial",
                "url": "http://twitter.com/newsycaitlin/status/441273812542160897",
                "trackback_date": 1394042850,
                "trackback_total": 0,
                "url_expansions": [],
                "target_birth_date": 1394042850,
                "content": "Then I had to say judicial, and judiciary 100 more times as a punishment. #prejudicial",
                "mytype": "tweet",
                "score": 4.887999,
                "topsy_author_img": "http://pbs.twimg.com/profile_images/3578987252/044cb8d13fd9cf77edb6b27fc03b052a_normal.jpeg",
                "trackback_permalink": "http://twitter.com/newsyCaitlin/status/441273812542160897",
                "trackback_author_url": "http://twitter.com/newsycaitlin",
                "highlight": "Then I had to say judicial, and judiciary 100 more times as a punishment.",
                "topsy_author_url": "http://topsy.com/twitter/newsycaitlin",
                "topsy_trackback_url": "http://topsy.com/trackback?url=http%3A//twitter.com/newsycaitlin/status/441273812542160897",
                "trackback_author_name": "Caitlin Burchill",
                "trackback_author_nick": "newsycaitlin"
            },
            {
                "hits": 1,
                "firstpost_date": 1305067566,
                "title": "qui nda @FernandesLucaas, levar sol demais \u00e9 #PREJUDICIAL  \u00e0 sa\u00fade!!!!!",
                "url": "http://twitter.com/vagnercandeia/status/68084425262505985",
                "trackback_date": 1305067566,
                "trackback_total": 0,
                "url_expansions": [],
                "target_birth_date": 1305067566,
                "content": "qui nda @FernandesLucaas, levar sol demais \u00e9 #PREJUDICIAL  \u00e0 sa\u00fade!!!!!",
                "mytype": "tweet",
                "score": 4.882742,
                "topsy_author_img": "http://pbs.twimg.com/profile_images/2679891055/14dc7cdd180263224561f127968ac48e_normal.jpeg",
                "trackback_permalink": "http://twitter.com/VagnerCandeia/status/68084425262505985",
                "trackback_author_url": "http://twitter.com/vagnercandeia",
                "highlight": "qui nda @FernandesLucaas, levar sol demais \u00e9 #PREJUDICIAL \u00e0 sa\u00fade!!!!!",
                "topsy_author_url": "http://topsy.com/twitter/vagnercandeia",
                "topsy_trackback_url": "http://topsy.com/trackback?url=http%3A//twitter.com/vagnercandeia/status/68084425262505985",
                "trackback_author_name": "VagnerCandeia",
                "trackback_author_nick": "vagnercandeia"
            },
            {
                "hits": 1,
                "firstpost_date": 1376405409,
                "title": "Maqubela amendments ' #prejudicial' #SouthAfrica http://t.co/iadHjYYac6 http://t.co/GmjFkwmzaj",
                "url": "http://twitter.com/newswallcoza/status/367297023210295296",
                "trackback_date": 1376405409,
                "trackback_total": 0,
                "url_expansions": [
                    {
                        "url": "http://t.co/iadHjYYac6",
                        "display_url": "bit.ly/17LeZP0",
                        "expanded_url": "http://bit.ly/17LeZP0",
                        "topsy_expanded_url": "http://newswall.co.za/news/latest/citizen/maqubela-amendments-8216-prejudicial-8217/ab1v5.221791"
                    },
                    {
                        "url": "http://t.co/GmjFkwmzaj",
                        "display_url": "twitpic.com/d83k4d",
                        "expanded_url": "http://twitpic.com/d83k4d",
                        "topsy_expanded_url": "http://twitpic.com/d83k4d"
                    }
                ],
                "target_birth_date": 1376405409,
                "content": "Maqubela amendments ' #prejudicial' #SouthAfrica http://t.co/iadHjYYac6 http://t.co/GmjFkwmzaj",
                "mytype": "tweet",
                "score": 4.8814464,
                "topsy_author_img": "http://pbs.twimg.com/profile_images/378800000084657415/07c56154457bdf9d6197cd926d43d2dc_normal.jpeg",
                "trackback_permalink": "http://twitter.com/NewsWallCoZa/status/367297023210295296",
                "trackback_author_url": "http://twitter.com/newswallcoza",
                "highlight": "Maqubela amendments ' #prejudicial' #SouthAfrica",
                "topsy_author_url": "http://topsy.com/twitter/newswallcoza",
                "topsy_trackback_url": "http://topsy.com/trackback?url=http%3A//twitter.com/newswallcoza/status/367297023210295296",
                "trackback_author_name": "NewsWall SouthAfrica",
                "trackback_author_nick": "newswallcoza"
            },
            {
                "hits": 1,
                "firstpost_date": 1334077200,
                "title": "Acordar de manh\u00e3 arrependido do que disse ou do que fez ontem \u00e0 noite \u00e9 #prejudicial \u00e0 sa\u00fade! ...",
                "url": "http://twitter.com/clarissets/status/189759649250156544",
                "trackback_date": 1334077200,
                "trackback_total": 0,
                "url_expansions": [],
                "target_birth_date": 1334077200,
                "content": "Acordar de manh\u00e3 arrependido do que disse ou do que fez ontem \u00e0 noite \u00e9 #prejudicial \u00e0 sa\u00fade! ...",
                "mytype": "tweet",
                "score": 4.877905,
                "topsy_author_img": "http://a0.twimg.com/profile_images/2957930194/00dfb31f34058aca2b4c9df33081e21c_normal.jpeg",
                "trackback_permalink": "http://twitter.com/Clarissets/status/189759649250156544",
                "trackback_author_url": "http://twitter.com/clarimedeiros2",
                "highlight": "Acordar de manh\u00e3 arrependido do que disse ou do que fez ontem \u00e0 noite \u00e9 #prejudicial \u00e0 sa\u00fade! ",
                "topsy_author_url": "http://topsy.com/twitter/clarimedeiros2",
                "topsy_trackback_url": "http://topsy.com/trackback?url=http%3A//twitter.com/clarissets/status/189759649250156544",
                "trackback_author_name": "Clari Medeiros",
                "trackback_author_nick": "clarimedeiros2"
            },
            {
                "hits": 1,
                "firstpost_date": 1375541553,
                "title": "Quero longe de mim pessoas pessimistas e que s\u00f3 veem o lado negativo dos outros.. #Prejudicial!",
                "url": "http://twitter.com/markflx/status/363673748970283009",
                "trackback_date": 1375541553,
                "trackback_total": 0,
                "url_expansions": [],
                "target_birth_date": 1375541553,
                "content": "Quero longe de mim pessoas pessimistas e que s\u00f3 veem o lado negativo dos outros.. #Prejudicial!",
                "mytype": "tweet",
                "score": 4.8777575,
                "topsy_author_img": "http://pbs.twimg.com/profile_images/3604572450/917bbcf5a58cad826daf024f9aa4a560_normal.jpeg",
                "trackback_permalink": "http://twitter.com/markflx/status/363673748970283009",
                "trackback_author_url": "http://twitter.com/markflx",
                "highlight": "Quero longe de mim pessoas pessimistas e que s\u00f3 veem o lado negativo dos outros.. #Prejudicial!",
                "topsy_author_url": "http://topsy.com/twitter/markflx",
                "topsy_trackback_url": "http://topsy.com/trackback?url=http%3A//twitter.com/markflx/status/363673748970283009",
                "trackback_author_name": "mark",
                "trackback_author_nick": "markflx"
            },
            {
                "hits": 2,
                "firstpost_date": 1391394822,
                "title": "THE RIGHTS OF THE DEFENDANT \nMR. TSARNAEV, ARE OF HIGH CONCERNS. WHEN REESTABLISHMENT OF RULE LAW, CAN IMPLEMENT A #PREJUDICIAL STATURE.",
                "url": "http://twitter.com/valens5527/status/430167181259571200",
                "trackback_date": 1391394822,
                "trackback_total": 1,
                "url_expansions": [],
                "target_birth_date": 1391394822,
                "content": "THE RIGHTS OF THE DEFENDANT \nMR. TSARNAEV, ARE OF HIGH CONCERNS. WHEN REESTABLISHMENT OF RULE LAW, CAN IMPLEMENT A #PREJUDICIAL STATURE.",
                "mytype": "tweet",
                "score": 4.8623085,
                "topsy_author_img": "http://pbs.twimg.com/profile_images/2642798135/69d1b713ff4656aaecce5bfe55a1fcb5_normal.jpeg",
                "trackback_permalink": "http://twitter.com/valens5527/status/430167181259571200",
                "trackback_author_url": "http://twitter.com/valens5527",
                "highlight": "THE RIGHTS OF THE DEFENDANT MR. TSARNAEV, ARE OF HIGH CONCERNS. WHEN REESTABLISHMENT OF RULE LAW, CAN IMPLEMENT A #PREJUDICIAL STATURE.",
                "topsy_author_url": "http://topsy.com/twitter/valens5527",
                "topsy_trackback_url": "http://topsy.com/trackback?url=http%3A//twitter.com/valens5527/status/430167181259571200",
                "trackback_author_name": "Beatrice Rivera",
                "trackback_author_nick": "valens5527"
            },
            {
                "hits": 2,
                "firstpost_date": 1373319063,
                "title": "That's fuckery tho the judge just allowed that? THC levels place into a selfdefense case I'm done watchin this! #Prejudicial #zimmermantrial",
                "url": "http://twitter.com/itzdsol/status/354351952479526912",
                "trackback_date": 1373319063,
                "trackback_total": 1,
                "url_expansions": [],
                "target_birth_date": 1373319063,
                "content": "That's fuckery tho the judge just allowed that? THC levels place into a selfdefense case I'm done watchin this! #Prejudicial #zimmermantrial",
                "mytype": "tweet",
                "score": 4.8539505,
                "topsy_author_img": "http://pbs.twimg.com/profile_images/466779659489652736/HKGyAHBE_normal.jpeg",
                "trackback_permalink": "http://twitter.com/itzDSOL/status/354351952479526912",
                "trackback_author_url": "http://twitter.com/itzdsol",
                "highlight": "That's fuckery tho the judge just allowed that? THC levels place into a selfdefense case I'm done watchin this! #Prejudicial",
                "topsy_author_url": "http://topsy.com/twitter/itzdsol",
                "topsy_trackback_url": "http://topsy.com/trackback?url=http%3A//twitter.com/itzdsol/status/354351952479526912",
                "trackback_author_name": "David Solomon",
                "trackback_author_nick": "itzdsol"
            },
            {
                "hits": 1,
                "firstpost_date": 1298481017,
                "title": "ai sim torna-se um #esporte #prejudicial.",
                "url": "http://twitter.com/maxcriciuma/status/40458437905223680",
                "trackback_date": 1298481017,
                "trackback_total": 0,
                "url_expansions": [],
                "target_birth_date": 1298481017,
                "content": "ai sim torna-se um #esporte #prejudicial.",
                "mytype": "tweet",
                "score": 4.853341,
                "topsy_author_img": "http://a0.twimg.com/profile_images/1251461973/logomaxxx__c_pia__normal.jpeg",
                "trackback_permalink": "http://twitter.com/maxcriciuma/status/40458437905223680",
                "trackback_author_url": "http://twitter.com/maxcriciuma",
                "highlight": "ai sim torna-se um #esporte #prejudicial.",
                "topsy_author_url": "http://topsy.com/twitter/maxcriciuma",
                "topsy_trackback_url": "http://topsy.com/trackback?url=http%3A//twitter.com/maxcriciuma/status/40458437905223680",
                "trackback_author_name": "MaxMuscle Nutrition ",
                "trackback_author_nick": "maxcriciuma"
            },
            {
                "hits": 1,
                "firstpost_date": 1379690388,
                "title": "Police say claims of Marikana evidence tampering ' #prejudicial' #SouthAfrica http://t.co/MGzzP0AU9T",
                "url": "http://twitter.com/marcel90674484/status/381075223862575104",
                "trackback_date": 1379690388,
                "trackback_total": 0,
                "url_expansions": [
                    {
                        "url": "http://t.co/MGzzP0AU9T",
                        "display_url": "bit.ly/16LHCyZ",
                        "expanded_url": "http://bit.ly/16LHCyZ",
                        "topsy_expanded_url": "http://newswall.co.za/news/latest/business-day/police-say-claims-of-marikana-evidence-tampering-prejudicial/b4ung.289760"
                    }
                ],
                "target_birth_date": 1379690388,
                "content": "Police say claims of Marikana evidence tampering ' #prejudicial' #SouthAfrica http://t.co/MGzzP0AU9T",
                "mytype": "tweet",
                "score": 4.850493,
                "topsy_author_img": "http://pbs.twimg.com/profile_images/2869244647/f21dda3033467db2188d50a322f0c73a_normal.jpeg",
                "trackback_permalink": "http://twitter.com/marcel90674484/status/381075223862575104",
                "trackback_author_url": "http://twitter.com/marcel90674484",
                "highlight": "Police say claims of Marikana evidence tampering ' #prejudicial' #SouthAfrica",
                "topsy_author_url": "http://topsy.com/twitter/marcel90674484",
                "topsy_trackback_url": "http://topsy.com/trackback?url=http%3A//twitter.com/marcel90674484/status/381075223862575104",
                "trackback_author_name": "The fourth kind ",
                "trackback_author_nick": "marcel90674484"
            }
        ],
        "last_offset": 10,
        "window": "a",
        "offset": 190,
        "hidden": 0,
        "total": 455,
        "page": 1
    }
}