{
    "request": {
        "url": "http://api-int:7000/search.json?q=%23torment&window=a&apikey=09C43A9B270A470B8EB8F2946A9369F3&type=tweet&offset=700",
        "resource": "search",
        "response_type": "json",
        "parameters": {
            "q": "#torment",
            "window": "a",
            "type": "tweet",
            "offset": "700"
        }
    },
    "response": {
        "perpage": 10,
        "list": [
            {
                "hits": 1,
                "firstpost_date": 1358383561,
                "title": "When we run from releasing and #forgiving that is where #torment comes in. Everything and everyone becomes a http://t.co/11gZw224",
                "url": "http://twitter.com/brenrenderos/status/291707916317241344",
                "trackback_date": 1358383561,
                "trackback_total": 0,
                "url_expansions": [
                    {
                        "url": "http://t.co/11gZw224",
                        "display_url": "instagr.am/p/UkLNloKXwi/",
                        "expanded_url": "http://instagr.am/p/UkLNloKXwi/",
                        "topsy_expanded_url": "http://instagram.com/p/UkLNloKXwi/"
                    }
                ],
                "target_birth_date": 1358383561,
                "content": "When we run from releasing and #forgiving that is where #torment comes in. Everything and everyone becomes a http://t.co/11gZw224",
                "mytype": "tweet",
                "score": 7.9809704,
                "topsy_author_img": "http://pbs.twimg.com/profile_images/439463286547828736/qQWlxXY8_normal.jpeg",
                "trackback_permalink": "http://twitter.com/BrenRenderos/status/291707916317241344",
                "trackback_author_url": "http://twitter.com/brenrenderos",
                "highlight": "When we run from releasing and #forgiving that is where #torment comes in. Everything and everyone becomes a",
                "topsy_author_url": "http://topsy.com/twitter/brenrenderos",
                "topsy_trackback_url": "http://topsy.com/trackback?url=http%3A//twitter.com/brenrenderos/status/291707916317241344",
                "trackback_author_name": "Brenda Renderos",
                "trackback_author_nick": "brenrenderos"
            },
            {
                "hits": 1,
                "firstpost_date": 1305426927,
                "title": "I am reading Torment http://bit.ly/mcHaKV @GetGlue #Torment",
                "url": "http://twitter.com/fernandacorreia/status/69591693405585408",
                "trackback_date": 1305426927,
                "trackback_total": 0,
                "url_expansions": [],
                "target_birth_date": 1305426927,
                "content": "I am reading Torment http://bit.ly/mcHaKV @GetGlue #Torment",
                "mytype": "tweet",
                "score": 7.9803443,
                "topsy_author_img": "http://pbs.twimg.com/profile_images/3448797512/c8c52c6e9792b1b4748a95c6700d39f9_normal.jpeg",
                "trackback_permalink": "http://twitter.com/fernandacorreia/status/69591693405585408",
                "trackback_author_url": "http://twitter.com/fernandacorreia",
                "highlight": "I am reading Torment @GetGlue",
                "topsy_author_url": "http://topsy.com/twitter/fernandacorreia",
                "topsy_trackback_url": "http://topsy.com/trackback?url=http%3A//twitter.com/fernandacorreia/status/69591693405585408",
                "trackback_author_name": "**Fefe**",
                "trackback_author_nick": "fernandacorreia"
            },
            {
                "hits": 2,
                "firstpost_date": 1297978914,
                "title": "Finished reading #Torment Today ... was amazing ... Can't wait for #Passion to come out by #LaurenKate #Fallen #TEAMDANIEL !",
                "url": "http://twitter.com/jenniieryckman/status/38352464923197440",
                "trackback_date": 1297978914,
                "trackback_total": 2,
                "url_expansions": [],
                "target_birth_date": 1297978914,
                "content": "Finished reading #Torment Today ... was amazing ... Can't wait for #Passion to come out by #LaurenKate #Fallen #TEAMDANIEL !",
                "mytype": "tweet",
                "score": 7.9792223,
                "topsy_author_img": "http://pbs.twimg.com/profile_images/469704298759467008/37e3eKVf_normal.jpeg",
                "trackback_permalink": "http://twitter.com/JenniieRyckman/status/38352464923197440",
                "trackback_author_url": "http://twitter.com/xdeaththekiddx",
                "highlight": "Finished reading #Torment Today ... was amazing ... Can't wait for #Passion to come out by #LaurenKate #Fallen #TEAMDANIEL !",
                "topsy_author_url": "http://topsy.com/twitter/xdeaththekiddx",
                "topsy_trackback_url": "http://topsy.com/trackback?url=http%3A//twitter.com/jenniieryckman/status/38352464923197440",
                "trackback_author_name": "Wretched & Divine",
                "trackback_author_nick": "xdeaththekiddx"
            },
            {
                "hits": 2,
                "firstpost_date": 1362577903,
                "title": "\u041a\u0430\u043c\u043f\u0430\u043d\u0438\u044f #Torment \u043d\u0430 #Kickstarter \u0441\u0442\u0430\u0440\u0442\u043e\u0432\u0430\u043b\u0430: http://t.co/nva0PYUNnz",
                "url": "http://twitter.com/geckusya/status/309300261510344704",
                "trackback_date": 1362577903,
                "trackback_total": 1,
                "url_expansions": [
                    {
                        "url": "http://t.co/nva0PYUNnz",
                        "display_url": "kck.st/168ny95",
                        "expanded_url": "http://kck.st/168ny95",
                        "topsy_expanded_url": "http://www.kickstarter.com/projects/inxile/torment-tides-of-numenera"
                    }
                ],
                "target_birth_date": 1362577903,
                "content": "\u041a\u0430\u043c\u043f\u0430\u043d\u0438\u044f #Torment \u043d\u0430 #Kickstarter \u0441\u0442\u0430\u0440\u0442\u043e\u0432\u0430\u043b\u0430: http://t.co/nva0PYUNnz",
                "mytype": "tweet",
                "score": 7.977833,
                "topsy_author_img": "http://pbs.twimg.com/profile_images/1866616047/ANY42_b_normal.png",
                "trackback_permalink": "http://twitter.com/geckusya/status/309300261510344704",
                "trackback_author_url": "http://twitter.com/geckusya",
                "highlight": "\u041a\u0430\u043c\u043f\u0430\u043d\u0438\u044f #Torment \u043d\u0430 #Kickstarter \u0441\u0442\u0430\u0440\u0442\u043e\u0432\u0430\u043b\u0430:",
                "topsy_author_url": "http://topsy.com/twitter/geckusya",
                "topsy_trackback_url": "http://topsy.com/trackback?url=http%3A//twitter.com/geckusya/status/309300261510344704",
                "trackback_author_name": "Gecko",
                "trackback_author_nick": "geckusya"
            },
            {
                "hits": 1,
                "firstpost_date": 1362593524,
                "title": "More excited about #Torment than #simcity no DRM no queues...",
                "url": "http://twitter.com/realzenfar/status/309365779621625857",
                "trackback_date": 1362593524,
                "trackback_total": 0,
                "url_expansions": [],
                "target_birth_date": 1362593524,
                "content": "More excited about #Torment than #simcity no DRM no queues...",
                "mytype": "tweet",
                "score": 7.9773626,
                "topsy_author_img": "http://pbs.twimg.com/profile_images/2497628013/8tzrwctmxwccbywvn88j_normal.png",
                "trackback_permalink": "http://twitter.com/RealZenfar/status/309365779621625857",
                "trackback_author_url": "http://twitter.com/realzenfar",
                "highlight": "More excited about #Torment than #simcity no DRM no queues",
                "topsy_author_url": "http://topsy.com/twitter/realzenfar",
                "topsy_trackback_url": "http://topsy.com/trackback?url=http%3A//twitter.com/realzenfar/status/309365779621625857",
                "trackback_author_name": "Zenfar",
                "trackback_author_nick": "realzenfar"
            },
            {
                "hits": 1,
                "firstpost_date": 1289306792,
                "title": "#torment - killing me inside",
                "url": "http://twitter.com/alvinnmh/status/1978945431932928",
                "trackback_date": 1289306792,
                "trackback_total": 0,
                "url_expansions": [],
                "target_birth_date": 1289306792,
                "content": "#torment - killing me inside",
                "mytype": "tweet",
                "score": 7.977053,
                "topsy_author_img": "http://a0.twimg.com/profile_images/2370268091/342412858_normal.jpg",
                "trackback_permalink": "http://twitter.com/alvinNMH/status/1978945431932928",
                "trackback_author_url": "http://twitter.com/alvinashad",
                "highlight": "#torment - killing me inside",
                "topsy_author_url": "http://topsy.com/twitter/alvinashad",
                "topsy_trackback_url": "http://topsy.com/trackback?url=http%3A//twitter.com/alvinnmh/status/1978945431932928",
                "trackback_author_name": "alvinashaD",
                "trackback_author_nick": "alvinashad"
            },
            {
                "hits": 1,
                "firstpost_date": 1328463127,
                "title": "Trapped in a car with a retired nuclear engineer. I keep having to do math. #torment #roadtrip",
                "url": "http://twitter.com/lilyorit/status/166212517931139073",
                "trackback_date": 1328463127,
                "trackback_total": 1,
                "url_expansions": [],
                "target_birth_date": 1328463127,
                "content": "Trapped in a car with a retired nuclear engineer. I keep having to do math. #torment #roadtrip",
                "mytype": "tweet",
                "score": 7.976265,
                "topsy_author_img": "http://pbs.twimg.com/profile_images/454391455088250880/zueklfMb_normal.jpeg",
                "trackback_permalink": "http://twitter.com/lilyorit/status/166212517931139073",
                "trackback_author_url": "http://twitter.com/lilyorit",
                "highlight": "Trapped in a car with a retired nuclear engineer. I keep having to do math. #torment",
                "topsy_author_url": "http://topsy.com/twitter/lilyorit",
                "topsy_trackback_url": "http://topsy.com/trackback?url=http%3A//twitter.com/lilyorit/status/166212517931139073",
                "trackback_author_name": "Lillian Cohen-Moore",
                "trackback_author_nick": "lilyorit"
            },
            {
                "hits": 1,
                "firstpost_date": 1358446118,
                "title": "\u3086\u3067\u305f\u307e\u8650\u3081  #Boiled #until #torment http://t.co/p3JQLtuy http://t.co/UTXpMBn3",
                "url": "http://twitter.com/reporters1/status/291970300885753857",
                "trackback_date": 1358446118,
                "trackback_total": 0,
                "url_expansions": [
                    {
                        "url": "http://t.co/p3JQLtuy",
                        "display_url": "nicoimage.com/z/vz5pc/",
                        "expanded_url": "http://nicoimage.com/z/vz5pc/",
                        "topsy_expanded_url": "http://nicoimage.com/o/1/15681/"
                    },
                    {
                        "url": "http://t.co/UTXpMBn3",
                        "display_url": "twitpic.com/bvylfd",
                        "expanded_url": "http://twitpic.com/bvylfd",
                        "topsy_expanded_url": "http://twitpic.com/bvylfd"
                    }
                ],
                "target_birth_date": 1358446118,
                "content": "\u3086\u3067\u305f\u307e\u8650\u3081  #Boiled #until #torment http://t.co/p3JQLtuy http://t.co/UTXpMBn3",
                "mytype": "tweet",
                "score": 7.975759,
                "topsy_author_img": "http://pbs.twimg.com/profile_images/2214863744/03m_normal.jpg",
                "trackback_permalink": "http://twitter.com/reporters1/status/291970300885753857",
                "trackback_author_url": "http://twitter.com/reporters1",
                "highlight": "\u3086\u3067\u305f\u307e\u8650\u3081 #Boiled #until #torment",
                "topsy_author_url": "http://topsy.com/twitter/reporters1",
                "topsy_trackback_url": "http://topsy.com/trackback?url=http%3A//twitter.com/reporters1/status/291970300885753857",
                "trackback_author_name": "reporter",
                "trackback_author_nick": "reporters1"
            },
            {
                "hits": 1,
                "firstpost_date": 1286688698,
                "title": "it seems better than the first #Torment http://bit.ly/cg2EZ0",
                "url": "http://twitter.com/apolloallyn/status/26911217604",
                "trackback_date": 1286688698,
                "trackback_total": 0,
                "url_expansions": [],
                "target_birth_date": 1286688698,
                "content": "it seems better than the first #Torment http://bit.ly/cg2EZ0",
                "mytype": "tweet",
                "score": 7.975391,
                "topsy_author_img": "http://pbs.twimg.com/profile_images/378800000360564443/437c67b4fe2f784769cc7b192e72f6e5_normal.jpeg",
                "trackback_permalink": "http://twitter.com/apolloallyn/status/26911217604",
                "trackback_author_url": "http://twitter.com/apolloallyn",
                "highlight": "it seems better than the first #Torment",
                "topsy_author_url": "http://topsy.com/twitter/apolloallyn",
                "topsy_trackback_url": "http://topsy.com/trackback?url=http%3A//twitter.com/apolloallyn/status/26911217604",
                "trackback_author_name": "apolloallyn",
                "trackback_author_nick": "apolloallyn"
            },
            {
                "hits": 1,
                "firstpost_date": 1291223558,
                "title": "Hoy comenzare a leer #Torment \u2665__\u2665",
                "url": "http://twitter.com/kihary/status/10018447194849280",
                "trackback_date": 1291223558,
                "trackback_total": 0,
                "url_expansions": [],
                "target_birth_date": 1291223558,
                "content": "Hoy comenzare a leer #Torment \u2665__\u2665",
                "mytype": "tweet",
                "score": 7.975102,
                "topsy_author_img": "http://pbs.twimg.com/profile_images/441269423358627840/M15tcWx-_normal.jpeg",
                "trackback_permalink": "http://twitter.com/Kihary/status/10018447194849280",
                "trackback_author_url": "http://twitter.com/kihary",
                "highlight": "Hoy comenzare a leer #Torment \u2665__\u2665",
                "topsy_author_url": "http://topsy.com/twitter/kihary",
                "topsy_trackback_url": "http://topsy.com/trackback?url=http%3A//twitter.com/kihary/status/10018447194849280",
                "trackback_author_name": "Katheryne L\u00f3pez",
                "trackback_author_nick": "kihary"
            }
        ],
        "last_offset": 10,
        "window": "a",
        "offset": 700,
        "hidden": 0,
        "total": 15210,
        "page": 1
    }
}