{
    "request": {
        "url": "http://api-int:7000/search.json?q=%23so-so&window=a&apikey=09C43A9B270A470B8EB8F2946A9369F3&type=tweet&offset=160",
        "resource": "search",
        "response_type": "json",
        "parameters": {
            "q": "#so-so",
            "window": "a",
            "type": "tweet",
            "offset": "160"
        }
    },
    "response": {
        "perpage": 10,
        "list": [
            {
                "hits": 1,
                "firstpost_date": 1294336534,
                "title": "ah barnet cut off......feeling funky again and ready to dance..thanks #so&so WB",
                "url": "http://twitter.com/decotedance/status/23075213331660800",
                "trackback_date": 1294336534,
                "trackback_total": 0,
                "url_expansions": [],
                "target_birth_date": 1294336534,
                "content": "ah barnet cut off......feeling funky again and ready to dance..thanks #so&so WB",
                "mytype": "tweet",
                "score": 7.6349025,
                "topsy_author_img": "http://pbs.twimg.com/profile_images/1097007742/decotebg_normal.jpg",
                "trackback_permalink": "http://twitter.com/decotedance/status/23075213331660800",
                "trackback_author_url": "http://twitter.com/decotedance",
                "highlight": "ah barnet cut off......feeling funky again and ready to dance..thanks #so&so WB",
                "topsy_author_url": "http://topsy.com/twitter/decotedance",
                "topsy_trackback_url": "http://topsy.com/trackback?url=http%3A//twitter.com/decotedance/status/23075213331660800",
                "trackback_author_name": "Jo-Anne Torre",
                "trackback_author_nick": "decotedance"
            },
            {
                "hits": 1,
                "firstpost_date": 1389975705,
                "title": "Adios Egypt..#so so",
                "url": "http://twitter.com/ardayudo/status/424214973032587264",
                "trackback_date": 1389975705,
                "trackback_total": 0,
                "url_expansions": [],
                "target_birth_date": 1389975705,
                "content": "Adios Egypt..#so so",
                "mytype": "tweet",
                "score": 7.633769,
                "topsy_author_img": "http://pbs.twimg.com/profile_images/447764921325871104/6kgWZyxW_normal.jpeg",
                "trackback_permalink": "http://twitter.com/ardayudo/status/424214973032587264",
                "trackback_author_url": "http://twitter.com/ardayudo",
                "highlight": "Adios Egypt..#so so",
                "topsy_author_url": "http://topsy.com/twitter/ardayudo",
                "topsy_trackback_url": "http://topsy.com/trackback?url=http%3A//twitter.com/ardayudo/status/424214973032587264",
                "trackback_author_name": "Yanuarda Yudo P.",
                "trackback_author_nick": "ardayudo"
            },
            {
                "hits": 1,
                "firstpost_date": 1309230788,
                "title": "niiiight. #sotired #sosore #so..so",
                "url": "http://twitter.com/tyhansen/status/85546241513095169",
                "trackback_date": 1309230788,
                "trackback_total": 0,
                "url_expansions": [],
                "target_birth_date": 1309230788,
                "content": "niiiight. #sotired #sosore #so..so",
                "mytype": "tweet",
                "score": 7.6334133,
                "topsy_author_img": "http://pbs.twimg.com/profile_images/454202301951930369/Ohu625Ot_normal.jpeg",
                "trackback_permalink": "http://twitter.com/TyHansen/status/85546241513095169",
                "trackback_author_url": "http://twitter.com/tyhansen",
                "highlight": "niiiight. #sotired #sosore #so..so",
                "topsy_author_url": "http://topsy.com/twitter/tyhansen",
                "topsy_trackback_url": "http://topsy.com/trackback?url=http%3A//twitter.com/tyhansen/status/85546241513095169",
                "trackback_author_name": "Ty Hansen",
                "trackback_author_nick": "tyhansen"
            },
            {
                "hits": 1,
                "firstpost_date": 1348504189,
                "title": "\u3061\u3087\u3063\u3068\u3060\u304b\u3089 \u30d0\u30a4\u30d0\u30a4 \u30d5\u30a1\u30c3\u30af\u3082\u3057\u30ca\u30a4\u30c8\u3057\u3093\u3058\u3083\u3046\u3088\u30fc(^_-) #so so",
                "url": "http://twitter.com/diamondnicehbpc/status/250270824647516160",
                "trackback_date": 1348504189,
                "trackback_total": 0,
                "url_expansions": [],
                "target_birth_date": 1348504189,
                "content": "\u3061\u3087\u3063\u3068\u3060\u304b\u3089 \u30d0\u30a4\u30d0\u30a4 \u30d5\u30a1\u30c3\u30af\u3082\u3057\u30ca\u30a4\u30c8\u3057\u3093\u3058\u3083\u3046\u3088\u30fc(^_-) #so so",
                "mytype": "tweet",
                "score": 7.6326284,
                "topsy_author_img": "http://pbs.twimg.com/profile_images/3059874709/427a9fe7d0ac7916a3730269e423b844_normal.jpeg",
                "trackback_permalink": "http://twitter.com/diamondnicehbpc/status/250270824647516160",
                "trackback_author_url": "http://twitter.com/diamondnicehbpc",
                "highlight": "\u3061\u3087\u3063\u3068\u3060\u304b\u3089 \u30d0\u30a4\u30d0\u30a4 \u30d5\u30a1\u30c3\u30af\u3082\u3057\u30ca\u30a4\u30c8\u3057\u3093\u3058\u3083\u3046\u3088\u30fc(^_-) #so so",
                "topsy_author_url": "http://topsy.com/twitter/diamondnicehbpc",
                "topsy_trackback_url": "http://topsy.com/trackback?url=http%3A//twitter.com/diamondnicehbpc/status/250270824647516160",
                "trackback_author_name": "DIAMONDNICE ",
                "trackback_author_nick": "diamondnicehbpc"
            },
            {
                "hits": 1,
                "firstpost_date": 1361776996,
                "title": "#So so SO disrespectful\" #BOY #mainvain http://t.co/9yaaReLXLm",
                "url": "http://twitter.com/boyrack87/status/305941015271985152",
                "trackback_date": 1361776996,
                "trackback_total": 0,
                "url_expansions": [
                    {
                        "url": "http://t.co/9yaaReLXLm",
                        "display_url": "instagr.am/p/WJTnS_lAVk/",
                        "expanded_url": "http://instagr.am/p/WJTnS_lAVk/",
                        "topsy_expanded_url": "http://instagram.com/p/WJTnS_lAVk/"
                    }
                ],
                "target_birth_date": 1361776996,
                "content": "#So so SO disrespectful\" #BOY #mainvain http://t.co/9yaaReLXLm",
                "mytype": "tweet",
                "score": 7.632085,
                "topsy_author_img": "http://pbs.twimg.com/profile_images/2505732792/profile_normal.jpg",
                "trackback_permalink": "http://twitter.com/boyrack87/status/305941015271985152",
                "trackback_author_url": "http://twitter.com/boyrack87",
                "highlight": "#So so SO disrespectful\" #BOY #mainvain",
                "topsy_author_url": "http://topsy.com/twitter/boyrack87",
                "topsy_trackback_url": "http://topsy.com/trackback?url=http%3A//twitter.com/boyrack87/status/305941015271985152",
                "trackback_author_name": "Anthony BOY Flores",
                "trackback_author_nick": "boyrack87"
            },
            {
                "hits": 1,
                "firstpost_date": 1328096054,
                "title": "#So so pasti kuman pun akan hilang [Like it? http://t.co/UkP4ADsO ]",
                "url": "http://twitter.com/fat_tandy/status/164672904695517184",
                "trackback_date": 1328096054,
                "trackback_total": 0,
                "url_expansions": [
                    {
                        "url": "http://t.co/UkP4ADsO",
                        "display_url": "goo.gl/Q4rV4",
                        "expanded_url": "http://goo.gl/Q4rV4",
                        "topsy_expanded_url": "http://www.likemytweets.com/tweet/164672880121098241"
                    }
                ],
                "target_birth_date": 1328096054,
                "content": "#So so pasti kuman pun akan hilang [Like it? http://t.co/UkP4ADsO ]",
                "mytype": "tweet",
                "score": 7.6314816,
                "topsy_author_img": "http://pbs.twimg.com/profile_images/468770046328590336/AOQfcJwX_normal.jpeg",
                "trackback_permalink": "http://twitter.com/fat_tandy/status/164672904695517184",
                "trackback_author_url": "http://twitter.com/fat_tandy",
                "highlight": "#So so pasti kuman pun akan hilang [Like it? ]",
                "topsy_author_url": "http://topsy.com/twitter/fat_tandy",
                "topsy_trackback_url": "http://topsy.com/trackback?url=http%3A//twitter.com/fat_tandy/status/164672904695517184",
                "trackback_author_name": "Hanri Patoding",
                "trackback_author_nick": "fat_tandy"
            },
            {
                "hits": 1,
                "firstpost_date": 1335954073,
                "title": "That moment when you text someone on bbm &amp; this comes up \"#so&amp;so does not have you as a contact. Do you wish to re-invite #so&amp;so? #SMH lol",
                "url": "http://twitter.com/masb_quik/status/197631826485985281",
                "trackback_date": 1335954073,
                "trackback_total": 0,
                "url_expansions": [],
                "target_birth_date": 1335954073,
                "content": "That moment when you text someone on bbm &amp; this comes up \"#so&amp;so does not have you as a contact. Do you wish to re-invite #so&amp;so? #SMH lol",
                "mytype": "tweet",
                "score": 7.631307,
                "topsy_author_img": "http://pbs.twimg.com/profile_images/474208990503919617/QmoeFw_Z_normal.jpeg",
                "trackback_permalink": "http://twitter.com/masb_quik/status/197631826485985281",
                "trackback_author_url": "http://twitter.com/masb_quik",
                "highlight": "That moment when you text someone on bbm &amp; this comes up \"#so&amp;so does not have you as a contact. Do you wish to re-invite #so&amp;so? #SMH lol",
                "topsy_author_url": "http://topsy.com/twitter/masb_quik",
                "topsy_trackback_url": "http://topsy.com/trackback?url=http%3A//twitter.com/masb_quik/status/197631826485985281",
                "trackback_author_name": "Sir Bhej ",
                "trackback_author_nick": "masb_quik"
            },
            {
                "hits": 1,
                "firstpost_date": 1305304383,
                "title": "cant help my feelings for #so&so",
                "url": "http://twitter.com/imrawaf/status/69077708352667648",
                "trackback_date": 1305304383,
                "trackback_total": 0,
                "url_expansions": [],
                "target_birth_date": 1305304383,
                "content": "cant help my feelings for #so&so",
                "mytype": "tweet",
                "score": 7.6305737,
                "topsy_author_img": "http://pbs.twimg.com/profile_images/444550021128544256/u6vd_4JL_normal.jpeg",
                "trackback_permalink": "http://twitter.com/IMRAWAF/status/69077708352667648",
                "trackback_author_url": "http://twitter.com/imrawaf",
                "highlight": "cant help my feelings for #so&so",
                "topsy_author_url": "http://topsy.com/twitter/imrawaf",
                "topsy_trackback_url": "http://topsy.com/trackback?url=http%3A//twitter.com/imrawaf/status/69077708352667648",
                "trackback_author_name": "J.Smith.",
                "trackback_author_nick": "imrawaf"
            },
            {
                "hits": 2,
                "firstpost_date": 1315411349,
                "title": "RT FOR PROMOTE!! #PROMO4PROMO #SO/SO #TEAMFOLLOWBACK #INSTANFOLLOWBACK",
                "url": "http://twitter.com/fridaylikejazz/status/111469396857331713",
                "trackback_date": 1315413490,
                "trackback_total": 3,
                "url_expansions": [],
                "target_birth_date": 1315411349,
                "content": "RT @FRIDAYLIKEJAZZ: RT FOR PROMOTE!! #PROMO4PROMO #SO/SO #TEAMFOLLOWBACK #INSTANFOLLOWBACK",
                "mytype": "tweet",
                "score": 7.628549,
                "topsy_author_img": "http://pbs.twimg.com/profile_images/439336739728285696/TACVN7aU_normal.jpeg",
                "trackback_permalink": "http://twitter.com/SpiritRider1/status/111478374471434240",
                "trackback_author_url": "http://twitter.com/spiritrider1",
                "highlight": "RT FOR PROMOTE!! #PROMO4PROMO #SO/SO #TEAMFOLLOWBACK",
                "topsy_author_url": "http://topsy.com/twitter/spiritrider1",
                "topsy_trackback_url": "http://topsy.com/trackback?url=http%3A//twitter.com/fridaylikejazz/status/111469396857331713",
                "trackback_author_name": "SpiritRider #TFB",
                "trackback_author_nick": "spiritrider1"
            },
            {
                "hits": 1,
                "firstpost_date": 1327010212,
                "title": "S/O @BUNJIGARLIN #hitafterhit #40ftRiddim #SO&SO",
                "url": "http://twitter.com/djspicemix/status/160118552018432001",
                "trackback_date": 1327010212,
                "trackback_total": 0,
                "url_expansions": [],
                "target_birth_date": 1327010212,
                "content": "S/O @BUNJIGARLIN #hitafterhit #40ftRiddim #SO&SO",
                "mytype": "tweet",
                "score": 7.627848,
                "topsy_author_img": "http://pbs.twimg.com/profile_images/378800000698970054/020cf8a343983bdf676f478c7e57afff_normal.jpeg",
                "trackback_permalink": "http://twitter.com/DJSpicemix/status/160118552018432001",
                "trackback_author_url": "http://twitter.com/djspicemix",
                "highlight": "S/O @BUNJIGARLIN #hitafterhit #40ftRiddim #SO&SO",
                "topsy_author_url": "http://topsy.com/twitter/djspicemix",
                "topsy_trackback_url": "http://topsy.com/trackback?url=http%3A//twitter.com/djspicemix/status/160118552018432001",
                "trackback_author_name": "DJ Spice",
                "trackback_author_nick": "djspicemix"
            }
        ],
        "last_offset": 10,
        "window": "a",
        "offset": 160,
        "hidden": 0,
        "total": 200095,
        "page": 1
    }
}