{
    "request": {
        "url": "http://api-int:7000/search.json?q=%23painful&window=a&apikey=09C43A9B270A470B8EB8F2946A9369F3&type=tweet&offset=630",
        "resource": "search",
        "response_type": "json",
        "parameters": {
            "q": "#painful",
            "window": "a",
            "type": "tweet",
            "offset": "630"
        }
    },
    "response": {
        "perpage": 10,
        "list": [
            {
                "hits": 2,
                "firstpost_date": 1268845584,
                "title": "#painful  watching swag artist in the position u deserve to be in",
                "url": "http://twitter.com/dashvillz/status/10630150093",
                "trackback_date": 1268845584,
                "trackback_total": 1,
                "url_expansions": [],
                "target_birth_date": 1268845584,
                "content": "#painful  watching swag artist in the position u deserve to be in",
                "mytype": "tweet",
                "score": 8.399796,
                "topsy_author_img": "http://pbs.twimg.com/profile_images/465942224946356224/x8PcaO40_normal.jpeg",
                "trackback_permalink": "http://twitter.com/DashVillz/status/10630150093",
                "trackback_author_url": "http://twitter.com/dashvillz",
                "highlight": "#painful watching swag artist in the position u deserve to be in",
                "topsy_author_url": "http://topsy.com/twitter/dashvillz",
                "topsy_trackback_url": "http://topsy.com/trackback?url=http%3A//twitter.com/dashvillz/status/10630150093",
                "trackback_author_name": "Officialdashvillz",
                "trackback_author_nick": "dashvillz"
            },
            {
                "hits": 2,
                "firstpost_date": 1316830568,
                "title": "98 mile per hour fastball Frazier just took off the wrist. #painful",
                "url": "http://twitter.com/brinkpg/status/117422033201139713",
                "trackback_date": 1316830568,
                "trackback_total": 1,
                "url_expansions": [],
                "target_birth_date": 1316830568,
                "content": "98 mile per hour fastball Frazier just took off the wrist. #painful",
                "mytype": "tweet",
                "score": 8.399719,
                "topsy_author_img": "http://pbs.twimg.com/profile_images/2431617315/image_normal.jpg",
                "trackback_permalink": "http://twitter.com/BrinkPG/status/117422033201139713",
                "trackback_author_url": "http://twitter.com/brinkpg",
                "highlight": "98 mile per hour fastball Frazier just took off the wrist.",
                "topsy_author_url": "http://topsy.com/twitter/brinkpg",
                "topsy_trackback_url": "http://topsy.com/trackback?url=http%3A//twitter.com/brinkpg/status/117422033201139713",
                "trackback_author_name": "Bill Brink",
                "trackback_author_nick": "brinkpg"
            },
            {
                "hits": 4,
                "firstpost_date": 1379064911,
                "title": "#BrightonSEO  #painful",
                "url": "http://twitter.com/ysekand/status/378451784848531456",
                "trackback_date": 1379064911,
                "trackback_total": 3,
                "url_expansions": [],
                "target_birth_date": 1379064911,
                "content": "#BrightonSEO  #painful",
                "mytype": "tweet",
                "score": 8.399236,
                "topsy_author_img": "http://pbs.twimg.com/profile_images/2676795406/7906387eb8923468487a52b5c7c939f1_normal.png",
                "trackback_permalink": "http://twitter.com/ysekand/status/378451784848531456",
                "trackback_author_url": "http://twitter.com/ysekand",
                "highlight": "#BrightonSEO",
                "topsy_author_url": "http://topsy.com/twitter/ysekand",
                "topsy_trackback_url": "http://topsy.com/trackback?url=http%3A//twitter.com/ysekand/status/378451784848531456",
                "trackback_author_name": "Yousaf",
                "trackback_author_nick": "ysekand"
            },
            {
                "hits": 3,
                "firstpost_date": 1305441176,
                "title": "Just cause you got MacBook and headphones doesn't mean you are a DJ ... They must stop this #painful #austin #Texas",
                "url": "http://twitter.com/centenodiego/status/69651458689204224",
                "trackback_date": 1305441176,
                "trackback_total": 3,
                "url_expansions": [],
                "target_birth_date": 1305441176,
                "content": "Just cause you got MacBook and headphones doesn't mean you are a DJ ... They must stop this #painful #austin #Texas",
                "mytype": "tweet",
                "score": 8.398639,
                "topsy_author_img": "http://pbs.twimg.com/profile_images/468609415185051652/p-CW3KTZ_normal.jpeg",
                "trackback_permalink": "http://twitter.com/CentenoDiego/status/69651458689204224",
                "trackback_author_url": "http://twitter.com/centenodiego",
                "highlight": "Just cause you got MacBook and headphones doesn't mean you are a DJ ... They must stop this #painful #austin",
                "topsy_author_url": "http://topsy.com/twitter/centenodiego",
                "topsy_trackback_url": "http://topsy.com/trackback?url=http%3A//twitter.com/centenodiego/status/69651458689204224",
                "trackback_author_name": "Diego Centeno",
                "trackback_author_nick": "centenodiego"
            },
            {
                "hits": 3,
                "firstpost_date": 1336285772,
                "title": "Toronto may b the 'screwface capital' but people haven't learned how to boo the wack shit yet #painful",
                "url": "http://twitter.com/hungree_mon/status/199023072601325571",
                "trackback_date": 1336285772,
                "trackback_total": 2,
                "url_expansions": [],
                "target_birth_date": 1336285772,
                "content": "Toronto may b the 'screwface capital' but people haven't learned how to boo the wack shit yet #painful",
                "mytype": "tweet",
                "score": 8.398507,
                "topsy_author_img": "http://pbs.twimg.com/profile_images/378800000295883100/96e5f1083367f54c2d37467bb8dd9799_normal.png",
                "trackback_permalink": "http://twitter.com/hungree_mon/status/199023072601325571",
                "trackback_author_url": "http://twitter.com/hungree_mon",
                "highlight": "Toronto may b the 'screwface capital' but people haven't learned how to boo the wack shit yet",
                "topsy_author_url": "http://topsy.com/twitter/hungree_mon",
                "topsy_trackback_url": "http://topsy.com/trackback?url=http%3A//twitter.com/hungree_mon/status/199023072601325571",
                "trackback_author_name": "HUNGREE",
                "trackback_author_nick": "hungree_mon"
            },
            {
                "hits": 2,
                "firstpost_date": 1258567298,
                "title": "Microsoft \u2014 well, at least they can dance: http://bit.ly/2bKNpN #painful #embarrassing #cringe-worthy #video via @wired",
                "url": "http://twitter.com/ilovetypography/status/5832648627",
                "trackback_date": 1258567298,
                "trackback_total": 4,
                "url_expansions": [],
                "target_birth_date": 1258567298,
                "content": "Microsoft \u2014 well, at least they can dance: http://bit.ly/2bKNpN #painful #embarrassing #cringe-worthy #video via @wired",
                "mytype": "tweet",
                "score": 8.398235,
                "topsy_author_img": "http://pbs.twimg.com/profile_images/1180684634/ilt_normal.png",
                "trackback_permalink": "http://twitter.com/ilovetypography/status/5832648627",
                "trackback_author_url": "http://twitter.com/ilovetypography",
                "highlight": "Microsoft \u2014 well, at least they can dance: #painful #embarrassing #cringe-worthy #video via @wired",
                "topsy_author_url": "http://topsy.com/twitter/ilovetypography",
                "topsy_trackback_url": "http://topsy.com/trackback?url=http%3A//twitter.com/ilovetypography/status/5832648627",
                "trackback_author_name": "I Love Typography",
                "trackback_author_nick": "ilovetypography"
            },
            {
                "hits": 1,
                "firstpost_date": 1309258277,
                "title": "Oh Jordan Paris. #painful",
                "url": "http://twitter.com/grogsgamut/status/85661541348818946",
                "trackback_date": 1309258277,
                "trackback_total": 0,
                "url_expansions": [],
                "target_birth_date": 1309258277,
                "content": "Oh Jordan Paris. #painful",
                "mytype": "tweet",
                "score": 8.397765,
                "topsy_author_img": "http://pbs.twimg.com/profile_images/1285347650/ralph_fiennes_normal.jpg",
                "trackback_permalink": "http://twitter.com/GrogsGamut/status/85661541348818946",
                "trackback_author_url": "http://twitter.com/grogsgamut",
                "highlight": "Oh Jordan Paris.",
                "topsy_author_url": "http://topsy.com/twitter/grogsgamut",
                "topsy_trackback_url": "http://topsy.com/trackback?url=http%3A//twitter.com/grogsgamut/status/85661541348818946",
                "trackback_author_name": "Greg Jericho",
                "trackback_author_nick": "grogsgamut"
            },
            {
                "hits": 4,
                "firstpost_date": 1341054435,
                "title": "Ouch. Mate of mine is the biggest Roses fan I know and he's gutted. Said it was shit. Listen to this! #painful http://t.co/Zr53byRA",
                "url": "http://twitter.com/shornkoomins/status/219024293491785730",
                "trackback_date": 1341054435,
                "trackback_total": 12,
                "url_expansions": [
                    {
                        "url": "http://t.co/Zr53byRA",
                        "display_url": "youtube.com/watch?v=kqoEYn\u2026",
                        "expanded_url": "http://www.youtube.com/watch?v=kqoEYn3ZxnE",
                        "topsy_expanded_url": "http://www.youtube.com/watch?v=kqoEYn3ZxnE"
                    }
                ],
                "target_birth_date": 1341054435,
                "content": "Ouch. Mate of mine is the biggest Roses fan I know and he's gutted. Said it was shit. Listen to this! #painful http://t.co/Zr53byRA",
                "mytype": "tweet",
                "score": 8.397432,
                "topsy_author_img": "http://pbs.twimg.com/profile_images/470505487562465282/o5bNLjuj_normal.jpeg",
                "trackback_permalink": "http://twitter.com/shornKOOMINS/status/219024293491785730",
                "trackback_author_url": "http://twitter.com/shornkoomins",
                "highlight": "Ouch. Mate of mine is the biggest Roses fan I know and he's gutted. Said it was shit. Listen to this! #painful",
                "topsy_author_url": "http://topsy.com/twitter/shornkoomins",
                "topsy_trackback_url": "http://topsy.com/trackback?url=http%3A//twitter.com/shornkoomins/status/219024293491785730",
                "trackback_author_name": "Sean",
                "trackback_author_nick": "shornkoomins"
            },
            {
                "hits": 2,
                "firstpost_date": 1400014207,
                "title": "Haha doing this random vid for @jackwills My #jwproperbritish Party Trick! #eyes #crosseyed #painful http://t.co/7xpQdcr4F7",
                "url": "http://twitter.com/abithamayo/status/466319500926021632",
                "trackback_date": 1400014207,
                "trackback_total": 1,
                "url_expansions": [
                    {
                        "url": "http://t.co/7xpQdcr4F7",
                        "display_url": "instagram.com/p/n83a9iGuWB/",
                        "expanded_url": "http://instagram.com/p/n83a9iGuWB/",
                        "topsy_expanded_url": "http://instagram.com/p/n83a9iGuWB/"
                    }
                ],
                "target_birth_date": 1400014207,
                "content": "Haha doing this random vid for @jackwills My #jwproperbritish Party Trick! #eyes #crosseyed #painful http://t.co/7xpQdcr4F7",
                "mytype": "tweet",
                "score": 8.396915,
                "topsy_author_img": "http://pbs.twimg.com/profile_images/467200468708786176/ISnNnPwu_normal.jpeg",
                "trackback_permalink": "http://twitter.com/AbithaMayo/status/466319500926021632",
                "trackback_author_url": "http://twitter.com/abithamayo",
                "highlight": "Haha doing this random vid for @jackwills My #jwproperbritish Party Trick! #eyes #crosseyed #painful",
                "topsy_author_url": "http://topsy.com/twitter/abithamayo",
                "topsy_trackback_url": "http://topsy.com/trackback?url=http%3A//twitter.com/abithamayo/status/466319500926021632",
                "trackback_author_name": "Abi Saunders",
                "trackback_author_nick": "abithamayo"
            },
            {
                "hits": 2,
                "firstpost_date": 1312057390,
                "title": "Kelly Rowland performing Motivation on Leno last night http://bit.ly/pPRf64 #painful #boring #awkward #unsexy",
                "url": "http://twitter.com/angryblkmandc/status/97401872071135232",
                "trackback_date": 1312057390,
                "trackback_total": 3,
                "url_expansions": [],
                "target_birth_date": 1312057390,
                "content": "Kelly Rowland performing Motivation on Leno last night http://bit.ly/pPRf64 #painful #boring #awkward #unsexy",
                "mytype": "tweet",
                "score": 8.393489,
                "topsy_author_img": "http://pbs.twimg.com/profile_images/1766350434/angry2_normal.jpg",
                "trackback_permalink": "http://twitter.com/AngryBlkManDC/status/97401872071135232",
                "trackback_author_url": "http://twitter.com/angryblkmandc",
                "highlight": "Kelly Rowland performing Motivation on Leno last night #painful #boring #awkward",
                "topsy_author_url": "http://topsy.com/twitter/angryblkmandc",
                "topsy_trackback_url": "http://topsy.com/trackback?url=http%3A//twitter.com/angryblkmandc/status/97401872071135232",
                "trackback_author_name": "Mr. ManSitChoAzzDown",
                "trackback_author_nick": "angryblkmandc"
            }
        ],
        "last_offset": 10,
        "window": "a",
        "offset": 630,
        "hidden": 0,
        "total": 680188,
        "page": 1
    }
}